sensecam_discovery/Camera.py
sensecam_discovery/Discover.py
sensecam_discovery/__init__.py
sensecam_discovery-2.2.2.dist-info/LICENSE
sensecam_discovery-2.2.2.dist-info/METADATA
sensecam_discovery-2.2.2.dist-info/WHEEL
sensecam_discovery-2.2.2.dist-info/top_level.txt
sensecam_discovery-2.2.2.dist-info/RECORD
