Metadata-Version: 2.1
Name: sensecam-discovery
Version: 2.2.2
Summary: A package to discover all onvif cameras on your network
Home-page: https://github.com/smartsenselab/sensecam-discovery
Author: Ricardo Barbosa Filho (Smart Sense Laboratory)
Author-email: ricardob@dcc.ufmg.br
License: UNKNOWN
Platform: UNKNOWN
Classifier: Natural Language :: English
Classifier: Programming Language :: Python :: 3.6
Classifier: License :: OSI Approved :: MIT License
Classifier: Operating System :: OS Independent
Classifier: Operating System :: Microsoft :: Windows
Classifier: Operating System :: POSIX
Requires-Python: >=3.6
Requires-Dist: WSDiscovery (==2.0.0)
Requires-Dist: netifaces (==0.10.9)
Requires-Dist: onvif-zeep (==0.2.12)
